jzchatbot/__init__.py
jzchatbot-59.84.0.dist-info/LICENSE
jzchatbot-59.84.0.dist-info/METADATA
jzchatbot-59.84.0.dist-info/WHEEL
jzchatbot-59.84.0.dist-info/top_level.txt
jzchatbot-59.84.0.dist-info/RECORD
