Metadata-Version: 2.1
Name: jzchatbot
Version: 59.84.0
Summary: A package that creates advanced AI chatbots
Author: JZ Enterprises
License: MIT
Requires-Python: >=3.8
License-File: LICENSE
Requires-Dist: pyttsx3
Requires-Dist: speechrecognition
Requires-Dist: nltk
Requires-Dist: textblob
